azure_openai_tr/__init__.py
azure_openai_tr/__main__.py
azure_openai_tr/azure_openai_tr.py
azure_openai_tr-0.1.0a5.dist-info/entry_points.txt
azure_openai_tr-0.1.0a5.dist-info/LICENSE
azure_openai_tr-0.1.0a5.dist-info/METADATA
azure_openai_tr-0.1.0a5.dist-info/WHEEL
azure_openai_tr-0.1.0a5.dist-info/RECORD
