Metadata-Version: 2.1
Name: azure-openai-tr
Version: 0.1.0a5
Summary: Translate via Azure Openai
Home-page: https://github.com/ffreemt/azure-openai-tr
License: MIT
Author: ffreemt
Requires-Python: >=3.10,<4.0
Classifier: License :: OSI Approved :: MIT License
Classifier: Programming Language :: Python :: 3
Classifier: Programming Language :: Python :: 3.10
Classifier: Programming Language :: Python :: 3.11
Requires-Dist: langchain (>=0.0.234,<0.0.235)
Requires-Dist: loguru (>=0.7.0,<0.8.0)
Requires-Dist: openai (>=0.27.8,<0.28.0)
Requires-Dist: set-loglevel (>=0.1.2,<0.2.0)
Requires-Dist: typer (>=0.4.1,<0.5.0)
Project-URL: Repository, https://github.com/ffreemt/azure-openai-tr
